weathercn/__init__.py
weathercn/__main__.py
weathercn/citycode.py
weathercn/font.py
weathercn/main.py
weathercn/paint.py
weathercn/parser.py
weathercn/picfinder.py
weathercn/reporter.py
weathercn/utils.py
weathercn/icons/down.png
weathercn/icons/pm.png
weathercn/icons/pm25.png
weathercn/icons/up.png
weathercn/icons/water.png
weathercn/icons/wind.png
py_weathercn-0.2.5.dist-info/METADATA
py_weathercn-0.2.5.dist-info/WHEEL
py_weathercn-0.2.5.dist-info/entry_points.txt
py_weathercn-0.2.5.dist-info/RECORD
