Metadata-Version: 2.4
Name: py-weathercn
Version: 0.2.5
Summary: 新版中国天气(weather.com.cn/weathern/) 爬虫 获取最新天气 以及天气日历数据
Author-email: ssfdust <ssfdust@gmail.com>
Requires-Python: >=3.8
Requires-Dist: arrow>=1.3.0
Requires-Dist: css-parser>=1.0.10
Requires-Dist: fclist-cffi>=1.1.2
Requires-Dist: pillow>=10.1.0
Requires-Dist: regex>=2023.12.25
Requires-Dist: requests>=2.31.0
